autocomplete/__init__.py
autocomplete/apps.py
autocomplete/core.py
autocomplete/shortcuts.py
autocomplete/views.py
autocomplete/widgets.py
autocomplete/locale/en/LC_MESSAGES/django.mo
autocomplete/locale/en/LC_MESSAGES/django.po
autocomplete/locale/fr/LC_MESSAGES/django.mo
autocomplete/locale/fr/LC_MESSAGES/django.po
autocomplete/static/autocomplete/css/autocomplete.css
autocomplete/static/autocomplete/js/autocomplete.js
autocomplete/templates/autocomplete/ac_container.html
autocomplete/templates/autocomplete/chip.html
autocomplete/templates/autocomplete/chip_list.html
autocomplete/templates/autocomplete/component.html
autocomplete/templates/autocomplete/head.html
autocomplete/templates/autocomplete/indicator-icon.html
autocomplete/templates/autocomplete/item.html
autocomplete/templates/autocomplete/item_list.html
autocomplete/templates/autocomplete/scripts.html
autocomplete/templates/autocomplete/textinput.html
autocomplete/templates/autocomplete/values.html
autocomplete/templates/autocomplete/strings/available_results.html
autocomplete/templates/autocomplete/strings/backspace_instruction.html
autocomplete/templates/autocomplete/strings/item_selected.html
autocomplete/templates/autocomplete/strings/multiselect.html
autocomplete/templates/autocomplete/strings/nothing_selected.html
autocomplete/templates/autocomplete/strings/selected.html
autocomplete/templatetags/__init__.py
autocomplete/templatetags/autocomplete.py
django_htmx_autocomplete-1.0.15.dist-info/licenses/LICENSE
sample_app/__init__.py
sample_app/admin.py
sample_app/apps.py
sample_app/asgi.py
sample_app/dev_script.py
sample_app/models.py
sample_app/settings.py
sample_app/tests.py
sample_app/urls.py
sample_app/views.py
sample_app/wsgi.py
sample_app/migrations/0001_initial.py
sample_app/migrations/__init__.py
tests/__init__.py
tests/conftest.py
tests/pytest_test_runner.py
tests/test_auth_check.py
tests/test_items.py
tests/test_model_ac.py
tests/test_sample_app_views.py
tests/test_toggle.py
tests/test_widget_render.py
tests/utils_for_test.py
django_htmx_autocomplete-1.0.15.dist-info/METADATA
django_htmx_autocomplete-1.0.15.dist-info/WHEEL
django_htmx_autocomplete-1.0.15.dist-info/top_level.txt
django_htmx_autocomplete-1.0.15.dist-info/RECORD
