Metadata-Version: 2.4
Name: django-htmx-autocomplete
Version: 1.0.15
Summary: A Django autocomplete component powered by htmx
Home-page: https://github.com/PHACDataHub/django-htmx-autocomplete
Author: Luc Belliveau
Author-email: luc.belliveau@canada.ca
License: MIT
Classifier: Environment :: Web Environment
Classifier: Framework :: Django
Classifier: Framework :: Django :: 4.1
Classifier: Intended Audience :: Developers
Classifier: License :: OSI Approved :: MIT License
Classifier: Operating System :: OS Independent
Classifier: Programming Language :: Python
Classifier: Programming Language :: Python :: 3
Classifier: Programming Language :: Python :: 3 :: Only
Classifier: Programming Language :: Python :: 3.8
Classifier: Programming Language :: Python :: 3.9
Classifier: Topic :: Internet :: WWW/HTTP
Classifier: Topic :: Internet :: WWW/HTTP :: Dynamic Content
Requires-Python: >=3.8
License-File: LICENSE
Requires-Dist: Django>=4.1
Dynamic: license-file
